oarepo_fsm/__init__.py
oarepo_fsm/config.py
oarepo_fsm/decorators.py
oarepo_fsm/errors.py
oarepo_fsm/ext.py
oarepo_fsm/links.py
oarepo_fsm/mixins.py
oarepo_fsm/permissions.py
oarepo_fsm/proxies.py
oarepo_fsm/version.py
oarepo_fsm/views.py
oarepo_fsm/datamodels/__init__.py
oarepo_fsm/datamodels/fsm-record-v2.0.0.json5
oarepo_fsm/included_mappings/v7/fsm-record-v2.0.0.json
oarepo_fsm/jsonschemas/__init__.py
oarepo_fsm/jsonschemas/fsm-record-v2.0.0.json
oarepo_fsm/marshmallow/__init__.py
oarepo_fsm-2.0.4.dist-info/AUTHORS.rst
oarepo_fsm-2.0.4.dist-info/LICENSE
oarepo_fsm-2.0.4.dist-info/METADATA
oarepo_fsm-2.0.4.dist-info/WHEEL
oarepo_fsm-2.0.4.dist-info/entry_points.txt
oarepo_fsm-2.0.4.dist-info/top_level.txt
oarepo_fsm-2.0.4.dist-info/RECORD
