Metadata-Version: 2.1
Name: oarepo-fsm
Version: 2.0.4
Summary: OArepo FSM library for record state transitions
Home-page: https://github.com/oarepo/oarepo-fsm
Author: CESNET
Author-email: bauer@cesnet.cz
License: MIT
Keywords: fsm fsm-library oarepo records state-management
Platform: any
Classifier: Environment :: Web Environment
Classifier: Intended Audience :: Developers
Classifier: License :: OSI Approved :: MIT License
Classifier: Operating System :: OS Independent
Classifier: Programming Language :: Python
Classifier: Topic :: Internet :: WWW/HTTP :: Dynamic Content
Classifier: Topic :: Software Development :: Libraries :: Python Modules
Classifier: Programming Language :: Python :: 2
Classifier: Programming Language :: Python :: 2.7
Classifier: Programming Language :: Python :: 3
Classifier: Programming Language :: Python :: 3.5
Classifier: Development Status :: 1 - Planning
License-File: LICENSE
License-File: AUTHORS.rst
Requires-Dist: wrapt (>=1.11.2)
Provides-Extra: build
Requires-Dist: oarepo-model-builder ; extra == 'build'
Provides-Extra: deploy
Requires-Dist: oarepo[deploy] (~=3.3.0) ; extra == 'deploy'
Provides-Extra: devel
Requires-Dist: oarepo[tests] (~=3.3.0) ; extra == 'devel'
Requires-Dist: Werkzeug (<2.0) ; extra == 'devel'
Provides-Extra: tests
Requires-Dist: oarepo[tests] (~=3.3.0) ; extra == 'tests'
Requires-Dist: Werkzeug (<2.0) ; extra == 'tests'
Provides-Extra: tests-es7
Requires-Dist: oarepo[tests-es7] (~=3.3.0) ; extra == 'tests-es7'
